{"name":"Login failed","id":"login;login-failed","testSteps":[{"number":1,"description":"Given He user is on the page","duration":355,"startTime":"2023-05-20T20:23:13.368-05:00[America/Bogota]","result":"SUCCESS","precondition":false,"level":0},{"number":2,"description":"When He user enter credentials","duration":4,"startTime":"2023-05-20T20:23:13.730-05:00[America/Bogota]","result":"PENDING","precondition":false,"level":0},{"number":3,"description":"Then He user couldn\u0027t see the his account","duration":3,"startTime":"2023-05-20T20:23:13.736-05:00[America/Bogota]","result":"IGNORED","precondition":false,"level":0}],"userStory":{"id":"login","storyName":"Login","path":"src/test/resources/features/login.feature","narrative":"  I as user, need start login to make use their services","type":"feature"},"featureTag":{"name":"Features/Login","type":"feature","displayName":"Features/Login"},"title":"Login failed","tags":[{"name":"Login","type":"feature","displayName":"Login"}],"startTime":"2023-05-20T20:23:13.173-05:00[America/Bogota]","duration":568,"projectKey":"","annotatedResult":"PENDING","isManualTestingUpToDate":false,"manual":false,"testSource":"Cucumber","result":"PENDING"}